{
  "expectedClusterCount": 6,
  "expectedDisplayText": "F#7alt",
  "expectedTopGlyphs": [
    "F",
    "#",
    "7",
    "a",
    "l",
    "t"
  ],
  "name": "FSharp7altCaptured01",
  "strokes": [
    {
      "bounds": {
        "maxX": 115.5,
        "maxY": 189.5,
        "minX": 114,
        "minY": 163.5
      },
      "points": [
        {
          "timeOffset": 0,
          "x": 114,
          "y": 163.5
        },
        {
          "timeOffset": 0.09954988956451416,
          "x": 114,
          "y": 166
        },
        {
          "timeOffset": 0.1162177324295044,
          "x": 114,
          "y": 170.5
        },
        {
          "timeOffset": 0.13288605213165283,
          "x": 114,
          "y": 176.5
        },
        {
          "timeOffset": 0.149574875831604,
          "x": 114.4743423461914,
          "y": 181.84188842773438
        },
        {
          "timeOffset": 0.16620874404907227,
          "x": 115.5,
          "y": 187
        },
        {
          "timeOffset": 0.1829087734222412,
          "x": 115.5,
          "y": 189
        },
        {
          "timeOffset": 0.19954383373260498,
          "x": 115.5,
          "y": 189.5
        }
      ]
    },
    {
      "bounds": {
        "maxX": 127,
        "maxY": 166,
        "minX": 114,
        "minY": 159
      },
      "points": [
        {
          "timeOffset": 0,
          "x": 114,
          "y": 166
        },
        {
          "timeOffset": 0.03305983543395996,
          "x": 114,
          "y": 164.5
        },
        {
          "timeOffset": 0.04964601993560791,
          "x": 118.9743423461914,
          "y": 163.34188842773438
        },
        {
          "timeOffset": 0.09963679313659668,
          "x": 123,
          "y": 162.5
        },
        {
          "timeOffset": 0.11636757850646973,
          "x": 125.16666412353516,
          "y": 160.6666717529297
        },
        {
          "timeOffset": 0.13298892974853516,
          "x": 127,
          "y": 159
        }
      ]
    },
    {
      "bounds": {
        "maxX": 123,
        "maxY": 177,
        "minX": 115.5,
        "minY": 175.5
      },
      "points": [
        {
          "timeOffset": 0,
          "x": 115.5,
          "y": 175.5
        },
        {
          "timeOffset": 0.033107876777648926,
          "x": 117,
          "y": 177
        },
        {
          "timeOffset": 0.049692630767822266,
          "x": 118.5,
          "y": 177
        },
        {
          "timeOffset": 0.08300387859344482,
          "x": 121.0256576538086,
          "y": 176.84188842773438
        },
        {
          "timeOffset": 0.09978711605072021,
          "x": 123,
          "y": 176.5
        }
      ]
    },
    {
      "bounds": {
        "maxX": 138.5,
        "maxY": 172.5,
        "minX": 137,
        "minY": 157
      },
      "points": [
        {
          "timeOffset": 0,
          "x": 137,
          "y": 159
        },
        {
          "timeOffset": 0.033205389976501465,
          "x": 137,
          "y": 157
        },
        {
          "timeOffset": 0.08321821689605713,
          "x": 138.09738159179688,
          "y": 162.79649353027344
        },
        {
          "timeOffset": 0.11652481555938721,
          "x": 138.5,
          "y": 167.5
        },
        {
          "timeOffset": 0.13318955898284912,
          "x": 138.5,
          "y": 170.5
        },
        {
          "timeOffset": 0.14984560012817383,
          "x": 138.5,
          "y": 172.5
        }
      ]
    },
    {
      "bounds": {
        "maxX": 144.5,
        "maxY": 170.5,
        "minX": 143,
        "minY": 156
      },
      "points": [
        {
          "timeOffset": 0,
          "x": 143,
          "y": 156
        },
        {
          "timeOffset": 0.0332798957824707,
          "x": 143,
          "y": 157.5
        },
        {
          "timeOffset": 0.04986560344696045,
          "x": 143,
          "y": 161
        },
        {
          "timeOffset": 0.066506028175354,
          "x": 143,
          "y": 164.5
        },
        {
          "timeOffset": 0.08317577838897705,
          "x": 143.3000030517578,
          "y": 168.10000610351562
        },
        {
          "timeOffset": 0.09983956813812256,
          "x": 144.5,
          "y": 170.5
        }
      ]
    },
    {
      "bounds": {
        "maxX": 146,
        "maxY": 165.5,
        "minX": 134.5,
        "minY": 161
      },
      "points": [
        {
          "timeOffset": 0,
          "x": 134.5,
          "y": 165.5
        },
        {
          "timeOffset": 0.028578996658325195,
          "x": 134.5,
          "y": 164
        },
        {
          "timeOffset": 0.06190943717956543,
          "x": 137,
          "y": 164
        },
        {
          "timeOffset": 0.07859301567077637,
          "x": 138.99319458007812,
          "y": 163.9178009033203
        },
        {
          "timeOffset": 0.09526705741882324,
          "x": 143,
          "y": 163.5
        },
        {
          "timeOffset": 0.11195850372314453,
          "x": 146,
          "y": 161
        }
      ]
    },
    {
      "bounds": {
        "maxX": 143,
        "maxY": 167.5,
        "minX": 134.5,
        "minY": 165.5
      },
      "points": [
        {
          "timeOffset": 0,
          "x": 137,
          "y": 167.5
        },
        {
          "timeOffset": 0.01634836196899414,
          "x": 134.5,
          "y": 167.5
        },
        {
          "timeOffset": 0.06619882583618164,
          "x": 137,
          "y": 167.5
        },
        {
          "timeOffset": 0.08291876316070557,
          "x": 143,
          "y": 165.5
        }
      ]
    },
    {
      "bounds": {
        "maxX": 162,
        "maxY": 171.5,
        "minX": 153,
        "minY": 153
      },
      "points": [
        {
          "timeOffset": 0,
          "x": 153,
          "y": 154
        },
        {
          "timeOffset": 0.08312833309173584,
          "x": 154.5,
          "y": 153.3333282470703
        },
        {
          "timeOffset": 0.09973859786987305,
          "x": 156,
          "y": 153.11111450195312
        },
        {
          "timeOffset": 0.11636960506439209,
          "x": 157.5,
          "y": 153.0370330810547
        },
        {
          "timeOffset": 0.13305377960205078,
          "x": 159,
          "y": 153
        },
        {
          "timeOffset": 0.149772047996521,
          "x": 161.77639770507812,
          "y": 153.4472198486328
        },
        {
          "timeOffset": 0.1996997594833374,
          "x": 162,
          "y": 156
        },
        {
          "timeOffset": 0.21636080741882324,
          "x": 160.5,
          "y": 160
        },
        {
          "timeOffset": 0.2330312728881836,
          "x": 159,
          "y": 164.5
        },
        {
          "timeOffset": 0.24969613552093506,
          "x": 157.7572479248047,
          "y": 168.57125854492188
        },
        {
          "timeOffset": 0.26636970043182373,
          "x": 157.5,
          "y": 171.5
        },
        {
          "timeOffset": 0.2996973991394043,
          "x": 157.5,
          "y": 170
        }
      ]
    },
    {
      "bounds": {
        "maxX": 179,
        "maxY": 180.5,
        "minX": 173.91603088378906,
        "minY": 170
      },
      "points": [
        {
          "timeOffset": 0,
          "x": 177.5,
          "y": 170
        },
        {
          "timeOffset": 0.1162787675857544,
          "x": 176.3333282470703,
          "y": 171.1666717529297
        },
        {
          "timeOffset": 0.13299572467803955,
          "x": 175.31234741210938,
          "y": 172.89044189453125
        },
        {
          "timeOffset": 0.1496272087097168,
          "x": 175,
          "y": 175.5
        },
        {
          "timeOffset": 0.16629278659820557,
          "x": 173.91603088378906,
          "y": 178.22265625
        },
        {
          "timeOffset": 0.18300354480743408,
          "x": 175,
          "y": 180.5
        },
        {
          "timeOffset": 0.21627092361450195,
          "x": 177.07125854492188,
          "y": 177.7427520751953
        },
        {
          "timeOffset": 0.23294270038604736,
          "x": 177.5,
          "y": 174
        },
        {
          "timeOffset": 0.24962067604064941,
          "x": 177.5,
          "y": 172.1666717529297
        },
        {
          "timeOffset": 0.26627683639526367,
          "x": 178.58914184570312,
          "y": 170.2849578857422
        },
        {
          "timeOffset": 0.29959213733673096,
          "x": 177.5,
          "y": 174
        },
        {
          "timeOffset": 0.33293819427490234,
          "x": 177.5,
          "y": 177
        },
        {
          "timeOffset": 0.3495924472808838,
          "x": 177.5,
          "y": 179.72222900390625
        },
        {
          "timeOffset": 0.383001446723938,
          "x": 179,
          "y": 180.5
        },
        {
          "timeOffset": 0.4330352544784546,
          "x": 179,
          "y": 179
        }
      ]
    },
    {
      "bounds": {
        "maxX": 188,
        "maxY": 180,
        "minX": 186.5,
        "minY": 163.5
      },
      "points": [
        {
          "timeOffset": 0,
          "x": 186.5,
          "y": 163.5
        },
        {
          "timeOffset": 0.08316695690155029,
          "x": 186.5,
          "y": 166.5
        },
        {
          "timeOffset": 0.0998222827911377,
          "x": 186.5,
          "y": 170.5
        },
        {
          "timeOffset": 0.11652100086212158,
          "x": 186.5,
          "y": 174.5
        },
        {
          "timeOffset": 0.13318955898284912,
          "x": 186.5,
          "y": 177
        },
        {
          "timeOffset": 0.14986801147460938,
          "x": 188,
          "y": 180
        }
      ]
    },
    {
      "bounds": {
        "maxX": 202.5,
        "maxY": 180.5,
        "minX": 199.5,
        "minY": 164
      },
      "points": [
        {
          "timeOffset": 0,
          "x": 199.5,
          "y": 164
        },
        {
          "timeOffset": 0.047705888748168945,
          "x": 199.5,
          "y": 167
        },
        {
          "timeOffset": 0.06438148021697998,
          "x": 199.5,
          "y": 170.5
        },
        {
          "timeOffset": 0.08103489875793457,
          "x": 201,
          "y": 174.5
        },
        {
          "timeOffset": 0.09767019748687744,
          "x": 202.5,
          "y": 178
        },
        {
          "timeOffset": 0.11441588401794434,
          "x": 202.5,
          "y": 180.5
        }
      ]
    },
    {
      "bounds": {
        "maxX": 204,
        "maxY": 176.5,
        "minX": 195,
        "minY": 174
      },
      "points": [
        {
          "timeOffset": 0,
          "x": 198,
          "y": 176.5
        },
        {
          "timeOffset": 0.01657545566558838,
          "x": 195,
          "y": 176.5
        },
        {
          "timeOffset": 0.0331268310546875,
          "x": 196.5,
          "y": 175.5
        },
        {
          "timeOffset": 0.0664910078048706,
          "x": 198,
          "y": 175
        },
        {
          "timeOffset": 0.08315277099609375,
          "x": 202.02566528320312,
          "y": 174.84188842773438
        },
        {
          "timeOffset": 0.09996449947357178,
          "x": 204,
          "y": 174
        }
      ]
    }
  ]
}
